<RelationList>
    <RelationPair>
        <Class1>DAOFactory</Class1>
        <Class2>DAOFactory</Class2>
        <RelationType>return</RelationType>
    </RelationPair>
    <RelationPair>
        <Class1>DAOFactory</Class1>
        <Class2>Connection</Class2>
        <RelationType>return</RelationType>
    </RelationPair>
    <RelationPair>
        <Class1>DAOFactory</Class1>
        <Class2>AccessDAO</Class2>
        <RelationType>return</RelationType>
    </RelationPair>
    <RelationPair>
        <Class1>DAOFactory</Class1>
        <Class2>ZipCodeDAO</Class2>
        <RelationType>return</RelationType>
    </RelationPair>
    <RelationPair>
        <Class1>DAOFactory</Class1>
        <Class2>AllergyDAO</Class2>
        <RelationType>return</RelationType>
    </RelationPair>
    <RelationPair>
        <Class1>DAOFactory</Class1>
        <Class2>ApptDAO</Class2>
        <RelationType>return</RelationType>
    </RelationPair>
    <RelationPair>
        <Class1>DAOFactory</Class1>
        <Class2>ApptRequestDAO</Class2>
        <RelationType>return</RelationType>
    </RelationPair>
    <RelationPair>
        <Class1>DAOFactory</Class1>
        <Class2>ApptTypeDAO</Class2>
        <RelationType>return</RelationType>
    </RelationPair>
    <RelationPair>
        <Class1>DAOFactory</Class1>
        <Class2>AuthDAO</Class2>
        <RelationType>return</RelationType>
    </RelationPair>
    <RelationPair>
        <Class1>DAOFactory</Class1>
        <Class2>BillingDAO</Class2>
        <RelationType>return</RelationType>
    </RelationPair>
    <RelationPair>
        <Class1>DAOFactory</Class1>
        <Class2>CPTCodesDAO</Class2>
        <RelationType>return</RelationType>
    </RelationPair>
    <RelationPair>
        <Class1>DAOFactory</Class1>
        <Class2>DrugInteractionDAO</Class2>
        <RelationType>return</RelationType>
    </RelationPair>
    <RelationPair>
        <Class1>DAOFactory</Class1>
        <Class2>FamilyDAO</Class2>
        <RelationType>return</RelationType>
    </RelationPair>
    <RelationPair>
        <Class1>DAOFactory</Class1>
        <Class2>HealthRecordsDAO</Class2>
        <RelationType>return</RelationType>
    </RelationPair>
    <RelationPair>
        <Class1>DAOFactory</Class1>
        <Class2>HospitalsDAO</Class2>
        <RelationType>return</RelationType>
    </RelationPair>
    <RelationPair>
        <Class1>DAOFactory</Class1>
        <Class2>ICDCodesDAO</Class2>
        <RelationType>return</RelationType>
    </RelationPair>
    <RelationPair>
        <Class1>DAOFactory</Class1>
        <Class2>NDCodesDAO</Class2>
        <RelationType>return</RelationType>
    </RelationPair>
    <RelationPair>
        <Class1>DAOFactory</Class1>
        <Class2>OfficeVisitDAO</Class2>
        <RelationType>return</RelationType>
    </RelationPair>
    <RelationPair>
        <Class1>DAOFactory</Class1>
        <Class2>PatientDAO</Class2>
        <RelationType>return</RelationType>
    </RelationPair>
    <RelationPair>
        <Class1>DAOFactory</Class1>
        <Class2>PersonnelDAO</Class2>
        <RelationType>return</RelationType>
    </RelationPair>
    <RelationPair>
        <Class1>DAOFactory</Class1>
        <Class2>ReferralDAO</Class2>
        <RelationType>return</RelationType>
    </RelationPair>
    <RelationPair>
        <Class1>DAOFactory</Class1>
        <Class2>RiskDAO</Class2>
        <RelationType>return</RelationType>
    </RelationPair>
    <RelationPair>
        <Class1>DAOFactory</Class1>
        <Class2>TransactionDAO</Class2>
        <RelationType>return</RelationType>
    </RelationPair>
    <RelationPair>
        <Class1>DAOFactory</Class1>
        <Class2>VisitRemindersDAO</Class2>
        <RelationType>return</RelationType>
    </RelationPair>
    <RelationPair>
        <Class1>DAOFactory</Class1>
        <Class2>FakeEmailDAO</Class2>
        <RelationType>return</RelationType>
    </RelationPair>
    <RelationPair>
        <Class1>DAOFactory</Class1>
        <Class2>ReportRequestDAO</Class2>
        <RelationType>return</RelationType>
    </RelationPair>
    <RelationPair>
        <Class1>DAOFactory</Class1>
        <Class2>SurveyDAO</Class2>
        <RelationType>return</RelationType>
    </RelationPair>
    <RelationPair>
        <Class1>DAOFactory</Class1>
        <Class2>LabProcedureDAO</Class2>
        <RelationType>return</RelationType>
    </RelationPair>
    <RelationPair>
        <Class1>DAOFactory</Class1>
        <Class2>LOINCDAO</Class2>
        <RelationType>return</RelationType>
    </RelationPair>
    <RelationPair>
        <Class1>DAOFactory</Class1>
        <Class2>SurveyResultDAO</Class2>
        <RelationType>return</RelationType>
    </RelationPair>
    <RelationPair>
        <Class1>DAOFactory</Class1>
        <Class2>MessageDAO</Class2>
        <RelationType>return</RelationType>
    </RelationPair>
    <RelationPair>
        <Class1>DAOFactory</Class1>
        <Class2>AdverseEventDAO</Class2>
        <RelationType>return</RelationType>
    </RelationPair>
    <RelationPair>
        <Class1>DAOFactory</Class1>
        <Class2>RemoteMonitoringDAO</Class2>
        <RelationType>return</RelationType>
    </RelationPair>
    <RelationPair>
        <Class1>DAOFactory</Class1>
        <Class2>PrescriptionsDAO</Class2>
        <RelationType>return</RelationType>
    </RelationPair>
    <RelationPair>
        <Class1>DAOFactory</Class1>
        <Class2>DiagnosesDAO</Class2>
        <RelationType>return</RelationType>
    </RelationPair>
    <RelationPair>
        <Class1>DAOFactory</Class1>
        <Class2>ProceduresDAO</Class2>
        <RelationType>return</RelationType>
    </RelationPair>
    <RelationPair>
        <Class1>DAOFactory</Class1>
        <Class2>PrescriptionReportDAO</Class2>
        <RelationType>return</RelationType>
    </RelationPair>
    <RelationPair>
        <Class1>DAOFactory</Class1>
        <Class2>DrugReactionOverrideCodesDAO</Class2>
        <RelationType>return</RelationType>
    </RelationPair>
    <RelationPair>
        <Class1>DAOFactory</Class1>
        <Class2>PatientInstructionsDAO</Class2>
        <RelationType>return</RelationType>
    </RelationPair>
    <RelationPair>
        <Class1>DAOFactory</Class1>
        <Class2>RequiredProceduresDAO</Class2>
        <RelationType>return</RelationType>
    </RelationPair>
    <RelationPair>
        <Class1>DAOFactory</Class1>
        <Class2>ReviewsDAO</Class2>
        <RelationType>return</RelationType>
    </RelationPair>
    <RelationPair>
        <Class1>DAOFactory</Class1>
        <Class2>OphthalmologyOVRecordDAO</Class2>
        <RelationType>return</RelationType>
    </RelationPair>
    <RelationPair>
        <Class1>DAOFactory</Class1>
        <Class2>OphthalmologyScheduleOVDAO</Class2>
        <RelationType>return</RelationType>
    </RelationPair>
    <RelationPair>
        <Class1>DAOFactory</Class1>
        <Class2>OphthalmologySurgeryRecordDAO</Class2>
        <RelationType>return</RelationType>
    </RelationPair>
    <RelationPair>
        <Class1>DAOFactory</Class1>
        <Class2>ObstetricsRecordDAO</Class2>
        <RelationType>return</RelationType>
    </RelationPair>
    <RelationPair>
        <Class1>DAOFactory</Class1>
        <Class2>FlagsDAO</Class2>
        <RelationType>return</RelationType>
    </RelationPair>
    <RelationPair>
        <Class1>DAOFactory</Class1>
        <Class2>PreExistingConditionsDAO</Class2>
        <RelationType>return</RelationType>
    </RelationPair>
    <RelationPair>
        <Class1>DAOFactory</Class1>
        <Class2>FoodEntryDAO</Class2>
        <RelationType>return</RelationType>
    </RelationPair>
    <RelationPair>
        <Class1>DAOFactory</Class1>
        <Class2>ExerciseEntryDAO</Class2>
        <RelationType>return</RelationType>
    </RelationPair>
    <RelationPair>
        <Class1>DAOFactory</Class1>
        <Class2>SleepEntryDAO</Class2>
        <RelationType>return</RelationType>
    </RelationPair>
    <RelationPair>
        <Class1>DAOFactory</Class1>
        <Class2>LabelDAO</Class2>
        <RelationType>return</RelationType>
    </RelationPair>
    <RelationPair>
        <Class1>DAOFactory</Class1>
        <Class2>MacronutrientsDAO</Class2>
        <RelationType>return</RelationType>
    </RelationPair>
    <RelationPair>
        <Class1>DAOFactory</Class1>
        <Class2>OphthalmologyDiagnosisDAO</Class2>
        <RelationType>return</RelationType>
    </RelationPair>
</RelationList>