<RelationList>
    <RelationPair>
        <Class1>AddOfficeVisitActionTest</Class1>
        <Class2>DAOFactory</Class2>
        <RelationType>attribute</RelationType>
    </RelationPair>
    <RelationPair>
        <Class1>AddOfficeVisitActionTest</Class1>
        <Class2>TestDataGenerator</Class2>
        <RelationType>attribute</RelationType>
    </RelationPair>
    <RelationPair>
        <Class1>AddOfficeVisitActionTest</Class1>
        <Class2>AddOfficeVisitAction</Class2>
        <RelationType>attribute</RelationType>
    </RelationPair>
</RelationList>