<RelationList>
    <RelationPair>
        <Class1>ReviewsBeanLoaderTest</Class1>
        <Class2>IMocksControl</Class2>
        <RelationType>attribute</RelationType>
    </RelationPair>
    <RelationPair>
        <Class1>ReviewsBeanLoaderTest</Class1>
        <Class2>ResultSet</Class2>
        <RelationType>attribute</RelationType>
    </RelationPair>
    <RelationPair>
        <Class1>ReviewsBeanLoaderTest</Class1>
        <Class2>ReviewsBeanLoader</Class2>
        <RelationType>attribute</RelationType>
    </RelationPair>
    <RelationPair>
        <Class1>ReviewsBeanLoaderTest</Class1>
        <Class2>ReviewsBean</Class2>
        <RelationType>attribute</RelationType>
    </RelationPair>
    <RelationPair>
        <Class1>ReviewsBeanLoaderTest</Class1>
        <Class2>long</Class2>
        <RelationType>attribute</RelationType>
    </RelationPair>
    <RelationPair>
        <Class1>ReviewsBeanLoaderTest</Class1>
        <Class2>long</Class2>
        <RelationType>attribute</RelationType>
    </RelationPair>
    <RelationPair>
        <Class1>ReviewsBeanLoaderTest</Class1>
        <Class2>int</Class2>
        <RelationType>attribute</RelationType>
    </RelationPair>
    <RelationPair>
        <Class1>ReviewsBeanLoaderTest</Class1>
        <Class2>Date</Class2>
        <RelationType>attribute</RelationType>
    </RelationPair>
    <RelationPair>
        <Class1>ReviewsBeanLoaderTest</Class1>
        <Class2>String</Class2>
        <RelationType>attribute</RelationType>
    </RelationPair>
</RelationList>