<RelationList>
    <RelationPair>
        <Class1>ICDCodesDAO</Class1>
        <Class2>DAOFactory</Class2>
        <RelationType>parameter</RelationType>
    </RelationPair>
    <RelationPair>
        <Class1>ICDCodesDAO</Class1>
        <Class2>String</Class2>
        <RelationType>parameter</RelationType>
    </RelationPair>
    <RelationPair>
        <Class1>ICDCodesDAO</Class1>
        <Class2>DiagnosisBean</Class2>
        <RelationType>parameter</RelationType>
    </RelationPair>
    <RelationPair>
        <Class1>ICDCodesDAO</Class1>
        <Class2>DiagnosisBean</Class2>
        <RelationType>parameter</RelationType>
    </RelationPair>
</RelationList>